company_graph/__init__.py
company_graph/cg.py
company_graph/func.py
company_graph/normalizer.py
company_graph/rules.py
company_graph/data/graph.pkl
company_graph-0.5.3.data/data/data/graph.pkl
company_graph-0.5.3.dist-info/LICENSE
company_graph-0.5.3.dist-info/METADATA
company_graph-0.5.3.dist-info/WHEEL
company_graph-0.5.3.dist-info/top_level.txt
company_graph-0.5.3.dist-info/RECORD
