Metadata-Version: 2.1
Name: company-graph
Version: 0.5.3
Summary: Resolving Messy Company Names
Home-page: https://github.com/estasney/CompanyGraph
Author: Eric Stasney
Author-email: estasney@users.noreply.github.com
License: MIT
Platform: UNKNOWN
Classifier: License :: OSI Approved :: MIT License
Classifier: Programming Language :: Python
Classifier: Programming Language :: Python :: 3
Classifier: Programming Language :: Python :: 3.7
Classifier: Programming Language :: Python :: 3.8
Classifier: Programming Language :: Python :: 3.9
Classifier: Programming Language :: Python :: 3.10
Requires-Python: >=3.7.0
License-File: LICENSE
Requires-Dist: networkx (>=2.6)
